typed_coinbaseexchange/__init__.py
typed_coinbaseexchange-0.1.0.dist-info/METADATA
typed_coinbaseexchange-0.1.0.dist-info/WHEEL
typed_coinbaseexchange-0.1.0.dist-info/top_level.txt
typed_coinbaseexchange-0.1.0.dist-info/RECORD
